{
    "message": "READ ONLY MODE: Request Successful",
    "data": {
        "id": "ceP1Cs",
        "name": "Five Hop - Experimental IPA",
        "nameDisplay": "Five Hop - Experimental IPA",
        "abv": "5.8",
        "ibu": "60",
        "styleId": 30,
        "isRetired": "N",
        "status": "verified",
        "statusDisplay": "Verified",
        "createDate": "2015-12-18 19:42:07",
        "updateDate": "2018-11-02 02:15:14",
        "style": {
            "id": 30,
            "categoryId": 3,
            "category": {
                "id": 3,
                "name": "North American Origin Ales",
                "createDate": "2012-03-21 20:06:45"
            },
            "name": "American-Style India Pale Ale",
            "shortName": "American IPA",
            "description": "American-style India pale ales are perceived to have medium-high to intense hop bitterness, flavor and aroma with medium-high alcohol content. The style is further characterized by floral, fruity, citrus-like, piney, resinous, or sulfur-like American-variety hop character. Note that one or more of these American-variety hop characters is the perceived end, but the hop characters may be a result of the skillful use of hops of other national origins. The use of water with high mineral content results in a crisp, dry beer. This pale gold to deep copper-colored ale has a full, flowery hop aroma and may have a strong hop flavor (in addition to the perception of hop bitterness). India pale ales possess medium maltiness which contributes to a medium body. Fruity-ester flavors and aromas are moderate to very strong. Diacetyl can be absent or may be perceived at very low levels. Chill and/or hop haze is allowable at cold temperatures. (English and citrus-like American hops are considered enough of a distinction justifying separate American-style IPA and English-style IPA categories or subcategories. Hops of other origins may be used for bitterness or approximating traditional American or English character. See English-style India Pale Ale",
            "ibuMin": "50",
            "ibuMax": "70",
            "abvMin": "6.3",
            "abvMax": "7.5",
            "srmMin": "6",
            "srmMax": "14",
            "ogMin": "1.06",
            "fgMin": "1.012",
            "fgMax": "1.018",
            "createDate": "2012-03-21 20:06:45",
            "updateDate": "2015-04-07 15:26:37"
        },
        "breweries": [
            {
                "id": "nHLlnK",
                "name": "Sierra Nevada Brewing Company",
                "nameShortDisplay": "Sierra Nevada",
                "status": "verified",
                "statusDisplay": "Verified",
                "createDate": "2012-01-03 02:42:08",
                "updateDate": "2018-11-02 02:15:01",
                "isInBusiness": "Y",
                "isVerified": "N",
                "locations": [
                    {
                        "id": "IaQrxj",
                        "name": "Main Brewery",
                        "streetAddress": "1075 East 20th St",
                        "locality": "Chico",
                        "region": "California",
                        "postalCode": "95928",
                        "phone": "530-893-3520",
                        "website": "http://www.sierranevada.com/",
                        "isPrimary": "Y",
                        "inPlanning": "N",
                        "isClosed": "N",
                        "openToPublic": "Y",
                        "locationType": "micro",
                        "locationTypeDisplay": "Micro Brewery",
                        "countryIsoCode": "US",
                        "yearOpened": "1980",
                        "status": "verified",
                        "statusDisplay": "Verified",
                        "createDate": "2012-01-03 02:42:08",
                        "updateDate": "2018-11-02 02:14:56",
                        "country": {
                            "isoCode": "US",
                            "name": "UNITED STATES",
                            "displayName": "United States",
                            "isoThree": "USA",
                            "numberCode": 840,
                            "createDate": "2012-01-03 02:41:33"
                        }
                    },
                    {
                        "id": "aqLvLE",
                        "name": "Asheville",
                        "streetAddress": "100 Sierra Nevada Way",
                        "locality": "Fletcher",
                        "region": "North Carolina",
                        "postalCode": "28732",
                        "isPrimary": "N",
                        "inPlanning": "N",
                        "isClosed": "N",
                        "openToPublic": "Y",
                        "locationType": "micro",
                        "locationTypeDisplay": "Micro Brewery",
                        "countryIsoCode": "US",
                        "status": "verified",
                        "statusDisplay": "Verified",
                        "createDate": "2012-03-29 20:56:05",
                        "updateDate": "2018-11-02 02:14:56",
                        "timezoneId": "America/New_York",
                        "country": {
                            "isoCode": "US",
                            "name": "UNITED STATES",
                            "displayName": "United States",
                            "isoThree": "USA",
                            "numberCode": 840,
                            "createDate": "2012-01-03 02:41:33"
                        }
                    }
                ]
            }
        ]
    },
    "status": "success"
}